HC_stock/__init__.py
HC_stock/stock.py
HC_stock-0.0.2.dist-info/LICENSE
HC_stock-0.0.2.dist-info/METADATA
HC_stock-0.0.2.dist-info/WHEEL
HC_stock-0.0.2.dist-info/top_level.txt
HC_stock-0.0.2.dist-info/RECORD
