Metadata-Version: 2.1
Name: HC-stock
Version: 0.0.2
Summary: Test pypi tools.
Home-page: http://www.4399.com
Author: liyifan
Author-email: liyifan@qq.com
License: Apache License
Platform: UNKNOWN
Classifier: Programming Language :: Python :: 3
Classifier: License :: OSI Approved :: MIT License
Classifier: Operating System :: OS Independent
Requires-Dist: matplotlib
Requires-Dist: bs4
Requires-Dist: requests
Requires-Dist: lxml
Requires-Dist: pandas
Requires-Dist: tushare
